cjm_parallel_utils/__init__.py
cjm_parallel_utils/_modidx.py
cjm_parallel_utils/core.py
cjm_parallel_utils/parallel_utils.py
cjm_parallel_utils-0.0.1.dist-info/LICENSE
cjm_parallel_utils-0.0.1.dist-info/METADATA
cjm_parallel_utils-0.0.1.dist-info/WHEEL
cjm_parallel_utils-0.0.1.dist-info/entry_points.txt
cjm_parallel_utils-0.0.1.dist-info/top_level.txt
cjm_parallel_utils-0.0.1.dist-info/RECORD
